{
  "sentiment": {
    "AAPL": {
      "score": 0.1733,
      "av_score": 0.1666,
      "finbert_score": 0.1889,
      "label": "Bullish",
      "num_articles": 50
    },
    "MSFT": {
      "score": 0.0725,
      "av_score": 0.0715,
      "finbert_score": 0.0747,
      "label": "Neutral",
      "num_articles": 50
    },
    "GOOGL": {
      "score": -0.0786,
      "av_score": -0.0477,
      "finbert_score": -0.1507,
      "label": "Neutral",
      "num_articles": 50
    },
    "AMZN": {
      "score": -0.0059,
      "av_score": 0.0534,
      "finbert_score": -0.1442,
      "label": "Neutral",
      "num_articles": 51
    },
    "TSLA": {
      "score": -0.1452,
      "av_score": -0.1248,
      "finbert_score": -0.1927,
      "label": "Bearish",
      "num_articles": 50
    },
    "JPM": {
      "score": 0.3833,
      "av_score": 0.1663,
      "finbert_score": 0.8897,
      "label": "Bullish",
      "num_articles": 50
    },
    "NVDA": {
      "score": 0.1806,
      "av_score": 0.2373,
      "finbert_score": 0.0482,
      "label": "Bullish",
      "num_articles": 50
    },
    "JNJ": {
      "score": 0.1507,
      "av_score": 0.2433,
      "finbert_score": -0.0655,
      "label": "Bullish",
      "num_articles": 50
    },
    "V": {
      "score": 0.3293,
      "av_score": 0.1892,
      "finbert_score": 0.6562,
      "label": "Bullish",
      "num_articles": 50
    },
    "KO": {
      "score": 0.0275,
      "av_score": 0.1189,
      "finbert_score": -0.1858,
      "label": "Bullish",
      "num_articles": 50
    },
    "ULVR.L": {
      "score": 0.0,
      "av_score": 0.0,
      "finbert_score": 0.0,
      "label": "neutral",
      "num_articles": 0
    },
    "HSBA.L": {
      "score": 0.0,
      "av_score": 0.0,
      "finbert_score": 0.0,
      "label": "neutral",
      "num_articles": 0
    },
    "BP.L": {
      "score": 0.0,
      "av_score": 0.0,
      "finbert_score": 0.0,
      "label": "neutral",
      "num_articles": 0
    },
    "GSK.L": {
      "score": 0.0,
      "av_score": 0.0,
      "finbert_score": 0.0,
      "label": "neutral",
      "num_articles": 0
    },
    "RIO.L": {
      "score": 0.0,
      "av_score": 0.0,
      "finbert_score": 0.0,
      "label": "neutral",
      "num_articles": 0
    },
    "ENI.MI": {
      "score": 0.0,
      "av_score": 0.0,
      "finbert_score": 0.0,
      "label": "neutral",
      "num_articles": 0
    },
    "ISP.MI": {
      "score": 0.0,
      "av_score": 0.0,
      "finbert_score": 0.0,
      "label": "neutral",
      "num_articles": 0
    },
    "ENEL.MI": {
      "score": 0.0,
      "av_score": 0.0,
      "finbert_score": 0.0,
      "label": "neutral",
      "num_articles": 0
    },
    "LDO.MI": {
      "score": 0.0,
      "av_score": 0.0,
      "finbert_score": 0.0,
      "label": "neutral",
      "num_articles": 0
    },
    "MONC.MI": {
      "score": 0.0,
      "av_score": 0.0,
      "finbert_score": 0.0,
      "label": "neutral",
      "num_articles": 0
    }
  },
  "fundamentals": {
    "AAPL": {
      "f_score": 0.5
    },
    "MSFT": {
      "f_score": 0.5
    },
    "GOOGL": {
      "f_score": 0.5
    },
    "AMZN": {
      "f_score": 0.5
    },
    "TSLA": {
      "f_score": 0.5
    },
    "JPM": {
      "f_score": 0.5
    },
    "NVDA": {
      "f_score": 0.5
    },
    "JNJ": {
      "f_score": 0.5
    },
    "V": {
      "f_score": 0.5
    },
    "KO": {
      "f_score": 0.5
    },
    "ULVR.L": {
      "f_score": 0.5
    },
    "HSBA.L": {
      "f_score": 0.5
    },
    "BP.L": {
      "f_score": 0.5
    },
    "GSK.L": {
      "f_score": 0.5
    },
    "RIO.L": {
      "f_score": 0.5
    },
    "ENI.MI": {
      "f_score": 0.5
    },
    "ISP.MI": {
      "f_score": 0.5
    },
    "ENEL.MI": {
      "f_score": 0.5
    },
    "LDO.MI": {
      "f_score": 0.5
    },
    "MONC.MI": {
      "f_score": 0.5
    }
  },
  "momentum": {
    "AAPL": {
      "return_3m": 0.0,
      "return_1m": 0.0
    },
    "MSFT": {
      "return_3m": 0.0,
      "return_1m": 0.0
    },
    "GOOGL": {
      "return_3m": 0.0,
      "return_1m": 0.0
    },
    "AMZN": {
      "return_3m": 0.0,
      "return_1m": 0.0
    },
    "TSLA": {
      "return_3m": 0.0,
      "return_1m": 0.0
    },
    "JPM": {
      "return_3m": 0.0,
      "return_1m": 0.0
    },
    "NVDA": {
      "return_3m": 0.0,
      "return_1m": 0.0
    },
    "JNJ": {
      "return_3m": 0.0,
      "return_1m": 0.0
    },
    "V": {
      "return_3m": 0.0,
      "return_1m": 0.0
    },
    "KO": {
      "return_3m": 0.0,
      "return_1m": 0.0
    },
    "ULVR.L": {
      "return_3m": 0.0,
      "return_1m": 0.0
    },
    "HSBA.L": {
      "return_3m": 0.0,
      "return_1m": 0.0
    },
    "BP.L": {
      "return_3m": 0.0,
      "return_1m": 0.0
    },
    "GSK.L": {
      "return_3m": 0.0,
      "return_1m": 0.0
    },
    "RIO.L": {
      "return_3m": 0.0,
      "return_1m": 0.0
    },
    "ENI.MI": {
      "return_3m": 0.0,
      "return_1m": 0.0
    },
    "ISP.MI": {
      "return_3m": 0.0,
      "return_1m": 0.0
    },
    "ENEL.MI": {
      "return_3m": 0.0,
      "return_1m": 0.0
    },
    "LDO.MI": {
      "return_3m": 0.0,
      "return_1m": 0.0
    },
    "MONC.MI": {
      "return_3m": 0.0,
      "return_1m": 0.0
    }
  },
  "sentiment_updated": "2026-07-24T07:58:29.139027+00:00",
  "fundamentals_updated": "2026-07-24T07:54:11.191867+00:00"
}